nbgrader_merge/__init__.py
nbgrader_merge/__main__.py
nbgrader_merge-0.1.1.dist-info/METADATA
nbgrader_merge-0.1.1.dist-info/RECORD
nbgrader_merge-0.1.1.dist-info/WHEEL
nbgrader_merge-0.1.1.dist-info/entry_points.txt
nbgrader_merge-0.1.1.dist-info/top_level.txt
