Metadata-Version: 2.1
Name: nbgrader-merge
Version: 0.1.1
Summary: Merge nbgrader exercise notebooks
Home-page: https://github.com/hcastilho/nbgrader_merge
Author: Hugo Castilho
Author-email: hcastilho@lisbondatascience.org
License: MIT license
Platform: UNKNOWN
Classifier: Development Status :: 2 - Pre-Alpha
Classifier: Intended Audience :: Developers
Classifier: License :: OSI Approved :: MIT License
Classifier: Natural Language :: English
Classifier: Programming Language :: Python :: 3
Classifier: Programming Language :: Python :: 3.5
Classifier: Programming Language :: Python :: 3.6
